dotenv_wizard/__init__.py
dotenv_wizard/cli.py
dotenv_wizard_savane-0.1.0.dist-info/METADATA
dotenv_wizard_savane-0.1.0.dist-info/WHEEL
dotenv_wizard_savane-0.1.0.dist-info/entry_points.txt
dotenv_wizard_savane-0.1.0.dist-info/top_level.txt
dotenv_wizard_savane-0.1.0.dist-info/RECORD
