Metadata-Version: 2.4
Name: dotenv-wizard-savane
Version: 0.1.0
Summary: Assistant CLI pour créer et gérer les fichiers .env dans vos projets Python
Author: SAVANE Mouhamed
Author-email: savanemouhamed05@gmail.com
License: MIT
Classifier: Programming Language :: Python :: 3
Classifier: License :: OSI Approved :: MIT License
Classifier: Operating System :: OS Independent
Classifier: Environment :: Console
Classifier: Intended Audience :: Developers
Requires-Python: >=3.6
Dynamic: author
Dynamic: author-email
Dynamic: classifier
Dynamic: description
Dynamic: description-content-type
Dynamic: license
Dynamic: requires-python
Dynamic: summary
